openal/__init__.py
openal/_al.py
openal/_alc.py
openal/al.py
openal/al_lib.py
openal/alc.py
openal/library_loader.py
openal/soft_oal_32.dll
PyOpenAL-0.7.11a1.dist-info/COPYING
PyOpenAL-0.7.11a1.dist-info/LICENSE
PyOpenAL-0.7.11a1.dist-info/METADATA
PyOpenAL-0.7.11a1.dist-info/WHEEL
PyOpenAL-0.7.11a1.dist-info/top_level.txt
PyOpenAL-0.7.11a1.dist-info/RECORD
