Metadata-Version: 2.1
Name: PyOpenAL
Version: 0.7.11a1
Summary: OpenAL integration for Python
Home-page: https://github.com/Zuzu-Typ/PyOpenAL
Author: Zuzu_Typ
Author-email: zuzu.typ@gmail.com
License: Unilicense
Keywords: OpenAL 3D game Xiph ogg vorbis opus sound playback audio
Platform: UNKNOWN
Classifier: Development Status :: 3 - Alpha
Classifier: Intended Audience :: Developers
Classifier: Topic :: Multimedia :: Sound/Audio
Classifier: Topic :: Games/Entertainment
Classifier: License :: Public Domain
Classifier: Programming Language :: Python :: 2
Classifier: Programming Language :: Python :: 2.7
Classifier: Programming Language :: Python :: 3
Classifier: Programming Language :: Python :: 3.3
Classifier: Programming Language :: Python :: 3.4
Classifier: Programming Language :: Python :: 3.5
Classifier: Programming Language :: Python :: 3.6
Classifier: Programming Language :: Python :: 3.7
Classifier: Programming Language :: Python :: 3.8
